{
  "$schema": "https://schema.management.azure.com/schemas/2018-05-01/subscriptionDeploymentTemplate.json#",
  "contentVersion": "1.0.0.0",
  "parameters": {
    "providerIdentities": {
      "type": "array",
      "defaultValue": [
      ]
    }
  },
  "variables": {
    "roleDefinition_Contributor": "[concat(subscription().id, '/providers/Microsoft.Authorization/roleDefinitions/b24988ac-6180-42a0-ab88-20f7382dd24c')]",
    "roleDefinition_UserAccessAdministrator": "[concat(subscription().id, '/providers/Microsoft.Authorization/roleDefinitions/18d7d88d-d35e-4fb5-a5c3-7773c20a72d9')]"
  },
  "resources": [
    {
      "condition": "[not(empty(parameters('providerIdentities')))]",
      "type": "Microsoft.Authorization/roleAssignments",
      "name": "[guid(resourceGroup().id, 'Contributor', string(copyIndex()))]",
      "apiVersion": "2017-10-01-preview",
      "properties": {
        "roleDefinitionId": "[variables('roleDefinition_Contributor')]",
        "principalId": "[parameters('providerIdentities')[copyIndex()]]",
        "scope": "[resourceGroup().Id]"
      },
      "copy": {
        "name": "contributorCopy",
        "count": "[length(parameters('providerIdentities'))]"
      }
    },
    {
      "condition": "[not(empty(parameters('providerIdentities')))]",
      "type": "Microsoft.Authorization/roleAssignments",
      "name": "[guid(resourceGroup().id, 'UserAccessAdministrator', string(copyIndex()))]",
      "apiVersion": "2017-10-01-preview",
      "properties": {
        "roleDefinitionId": "[variables('roleDefinition_UserAccessAdministrator')]",
        "principalId": "[parameters('providerIdentities')[copyIndex()]]",
        "scope": "[resourceGroup().Id]"
      },
      "copy": {
        "name": "userAccessAdministratorCopy",
        "count": "[length(parameters('providerIdentities'))]"
      }
    }
  ],
  "outputs": {
  }
}
